{
  "GUID": "e6fef2",
  "Name": "DeckCustom",
  "Transform": {
    "posX": -62.2506371,
    "posY": 1.6677947,
    "posZ": 5.249995,
    "rotX": 0.0798788741,
    "rotY": 90.00829,
    "rotZ": 359.983154,
    "scaleX": 3.2,
    "scaleY": 1.0,
    "scaleZ": 3.2
  },
  "Nickname": "Alien/Exiled Race Deck",
  "Description": "",
  "GMNotes": "",
  "AltLookAngle": {
    "x": 0.0,
    "y": 0.0,
    "z": 0.0
  },
  "ColorDiffuse": {
    "r": 0.713235259,
    "g": 0.713235259,
    "b": 0.713235259
  },
  "LayoutGroupSortIndex": 0,
  "Value": 0,
  "Locked": true,
  "Grid": true,
  "Snap": true,
  "IgnoreFoW": false,
  "MeasureMovement": false,
  "DragSelectable": true,
  "Autoraise": true,
  "Sticky": true,
  "Tooltip": true,
  "GridProjection": false,
  "HideWhenFaceDown": false,
  "Hands": false,
  "SidewaysCard": false,
  "DeckIDs": [
    9115,
    9114,
    9113,
    9108,
    9102,
    9105,
    9112,
    9104,
    9100,
    9109,
    9110,
    9103,
    9101,
    9111,
    9106,
    9107
  ],
  "CustomDeck": {
    "91": {
      "FaceURL": "https://steamusercontent-a.akamaihd.net/ugc/16928982173363141655/491031C129191A59EDC577C7F70B58F40371F6EF/",
      "BackURL": "https://steamusercontent-a.akamaihd.net/ugc/16503309906513791723/10C7C21F9B276DEEF3B5DC3EA83F36023583ED50/",
      "NumWidth": 6,
      "NumHeight": 3,
      "BackIsHidden": true,
      "UniqueBack": true,
      "Type": 0
    }
  }
}